ckcc/__init__.py
ckcc/cli.py
ckcc/client.py
ckcc/constants.py
ckcc/electrum.py
ckcc/protocol.py
ckcc/sigheader.py
ckcc/utils.py
ckcc_protocol-1.5.0.dist-info/COPYING-CC
ckcc_protocol-1.5.0.dist-info/METADATA
ckcc_protocol-1.5.0.dist-info/WHEEL
ckcc_protocol-1.5.0.dist-info/entry_points.txt
ckcc_protocol-1.5.0.dist-info/top_level.txt
ckcc_protocol-1.5.0.dist-info/RECORD
