Metadata-Version: 2.1
Name: ckcc-protocol
Version: 1.5.0
Summary: Communicate with your Coldcard using Python
Home-page: https://github.com/Coldcard/ckcc-protocol
Author: Coinkite Inc.
Author-email: support@coinkite.com
Classifier: Operating System :: POSIX :: Linux
Classifier: Operating System :: Microsoft :: Windows
Classifier: Operating System :: MacOS :: MacOS X
Requires-Python: >3.6.0
License-File: COPYING-CC
Requires-Dist: hidapi (>=0.7.99.post21)
Requires-Dist: ecdsa (>=0.17)
Requires-Dist: pyaes
Provides-Extra: cli
Requires-Dist: click (>=6.7) ; extra == 'cli'
